fogbed/__init__.py
fogbed/emulation.py
fogbed/exceptions.py
fogbed/helpers.py
fogbed/scripts.py
fogbed/experiment/__init__.py
fogbed/experiment/distributed.py
fogbed/experiment/local.py
fogbed/experiment/net.py
fogbed/node/__init__.py
fogbed/node/container.py
fogbed/node/controller.py
fogbed/node/instance.py
fogbed/node/link.py
fogbed/node/worker.py
fogbed/node/services/__init__.py
fogbed/node/services/local_docker.py
fogbed/node/services/remote_docker.py
fogbed/parsing/__init__.py
fogbed/parsing/builder.py
fogbed/parsing/dto.py
fogbed/parsing/exceptions.py
fogbed/parsing/messages.py
fogbed/parsing/parser.py
fogbed/parsing/factories/__init__.py
fogbed/parsing/factories/distributed.py
fogbed/parsing/factories/local.py
fogbed/resources/__init__.py
fogbed/resources/allocation.py
fogbed/resources/flavors.py
fogbed/resources/models.py
fogbed/resources/protocols.py
fogbed-1.3.0.dist-info/METADATA
fogbed-1.3.0.dist-info/WHEEL
fogbed-1.3.0.dist-info/entry_points.txt
fogbed-1.3.0.dist-info/top_level.txt
fogbed-1.3.0.dist-info/RECORD
