Metadata-Version: 2.4
Name: fogbed
Version: 1.3.0
Summary: Fog and edge computing emulation platform.
Author: Esaú Mascarenhas and Antonio Coutinho
License: MIT License
Project-URL: Homepage, https://larsid.github.io/fogbed
Keywords: networking,emulator,protocol,Internet,OpenFlow,SDN,fog,edge
Classifier: Development Status :: 5 - Production/Stable
Classifier: Programming Language :: Python :: 3.8
Classifier: Intended Audience :: Developers
Classifier: Topic :: System :: Distributed Computing
Classifier: Topic :: System :: Emulators
Requires-Python: >=3.8
Requires-Dist: clusternet>=0.9.3
Requires-Dist: urllib3>=1.26.0
